AWSScout2/__init__.py
AWSScout2/__listall__.py
AWSScout2/__main__.py
AWSScout2/__rules_generator__.py
AWSScout2/cli_parser.py
AWSScout2/utils.py
AWSScout2/configs/__init__.py
AWSScout2/configs/base.py
AWSScout2/configs/browser.py
AWSScout2/configs/regions.py
AWSScout2/configs/scout2.py
AWSScout2/configs/services.py
AWSScout2/configs/threads.py
AWSScout2/configs/vpc.py
AWSScout2/configs/data/metadata.json
AWSScout2/data/requirements.txt
AWSScout2/output/__init__.py
AWSScout2/output/console.py
AWSScout2/output/html.py
AWSScout2/output/js.py
AWSScout2/output/utils.py
AWSScout2/output/data/includes.zip
AWSScout2/output/data/html/report.html
AWSScout2/output/data/html/ruleset-generator.html
AWSScout2/output/data/html/partials/accordion.html
AWSScout2/output/data/html/partials/accordion_policy.html
AWSScout2/output/data/html/partials/dashboard.html
AWSScout2/output/data/html/partials/details.html
AWSScout2/output/data/html/partials/details_for_region.html
AWSScout2/output/data/html/partials/details_for_vpc.html
AWSScout2/output/data/html/partials/ec2_grants.html
AWSScout2/output/data/html/partials/filters.html
AWSScout2/output/data/html/partials/generic_object.html
AWSScout2/output/data/html/partials/ip_grants.html
AWSScout2/output/data/html/partials/left_menu.html
AWSScout2/output/data/html/partials/left_menu_for_region.html
AWSScout2/output/data/html/partials/left_menu_for_vpc.html
AWSScout2/output/data/html/partials/metadata.html
AWSScout2/output/data/html/partials/network_interface.html
AWSScout2/output/data/html/partials/policy.html
AWSScout2/output/data/html/partials/regionfilters.html
AWSScout2/output/data/html/partials/resource_link.html
AWSScout2/output/data/html/partials/services.awslambda.regions.id.functions.html
AWSScout2/output/data/html/partials/services.cloudformation.regions.id.stacks.html
AWSScout2/output/data/html/partials/services.cloudtrail.regions.html
AWSScout2/output/data/html/partials/services.cloudtrail.regions.id.trails.html
AWSScout2-3.2.1.dist-info/LICENSE
AWSScout2-3.2.1.dist-info/METADATA
AWSScout2-3.2.1.dist-info/WHEEL
AWSScout2-3.2.1.dist-info/entry_points.txt
AWSScout2-3.2.1.dist-info/top_level.txt
AWSScout2-3.2.1.dist-info/RECORD
